fireredtts2/__init__.py
fireredtts2/fireredtts2.py
fireredtts2/codec/__init__.py
fireredtts2/codec/audio.py
fireredtts2/codec/decoder.py
fireredtts2/codec/model.py
fireredtts2/codec/rvq.py
fireredtts2/codec/utils.py
fireredtts2/codec/whisper.py
fireredtts2/llm/__init__.py
fireredtts2/llm/llm.py
fireredtts2/llm/modules.py
fireredtts2/llm/utils.py
fireredtts2/utils/__init__.py
fireredtts2/utils/spliter.py
tts_webui_fireredtts2-0.1.0.dist-info/licenses/LICENSE
tts_webui_fireredtts2-0.1.0.dist-info/METADATA
tts_webui_fireredtts2-0.1.0.dist-info/WHEEL
tts_webui_fireredtts2-0.1.0.dist-info/top_level.txt
tts_webui_fireredtts2-0.1.0.dist-info/RECORD
