Metadata-Version: 2.4
Name: tts-webui.fireredtts2
Version: 0.1.0
Summary: FireRedTTS2 - speech generation utilities and model wrapper
Author: FireRedTTS2
Requires-Python: >=3.8
License-File: LICENSE
Requires-Dist: torchtune
Requires-Dist: torchao
Requires-Dist: transformers
Requires-Dist: einops
Requires-Dist: gradio
Dynamic: author
Dynamic: description
Dynamic: description-content-type
Dynamic: license-file
Dynamic: requires-dist
Dynamic: requires-python
Dynamic: summary
